[
  {"point": [0.0, -3.1999998, 0.79999995]},
  {"point": [0.0, 0.0, 0.79999995]},
  {"point": [0.56, -3.1999998, 0.56]},
  {"point": [0.56, 0.0, 0.56]},
  {"point": [0.79999995, -3.1999998, 0.0]},
  {"point": [0.79999995, 0.0, 0.0]},
  {"point": [0.56, -3.1999998, -0.56]},
  {"point": [0.56, 0.0, -0.56]},
  {"point": [0.0, -3.1999998, -0.79999995]},
  {"point": [0.0, 0.0, -0.79999995]},
  {"point": [-0.56, -3.1999998, -0.56]},
  {"point": [-0.56, 0.0, -0.56]},
  {"point": [-0.79999995, -3.1999998, 0.0]},
  {"point": [-0.79999995, 0.0, 0.0]},
  {"point": [-0.56, -3.1999998, 0.56]},
  {"point": [-0.56, 0.0, 0.56]},
  {"point": [0.12, -2.0, 1.38]},
  {"point": [0.12, 0.0, 1.38]},
  {"point": [0.74, -2.0, 1.16]},
  {"point": [0.74, 0.0, 1.16]},
  {"point": [1.1999999, -2.0, 0.68]},
  {"point": [1.1999999, 0.0, 0.68]},
  {"point": [1.38, -2.0, 0.04]},
  {"point": [1.38, 0.0, 0.04]},
  {"point": [1.26, -2.0, -0.59999996]},
  {"point": [1.26, 0.0, -0.59999996]},
  {"point": [0.82, -2.0, -1.12]},
  {"point": [0.82, 0.0, -1.12]},
  {"point": [0.19999999, -2.0, -1.38]},
  {"point": [0.19999999, 0.0, -1.38]},
  {"point": [-0.44, -2.0, -1.3199999]},
  {"point": [-0.44, 0.0, -1.3199999]},
  {"point": [-1.0, -2.0, -0.96]},
  {"point": [-1.0, 0.0, -0.96]},
  {"point": [-1.3399999, -2.0, -0.38]},
  {"point": [-1.3399999, 0.0, -0.38]},
  {"point": [-1.36, -2.0, 0.28]},
  {"point": [-1.36, 0.0, 0.28]},
  {"point": [-1.06, -2.0, 0.88]},
  {"point": [-1.06, 0.0, 0.88]},
  {"point": [-0.53999996, -2.0, 1.28]},
  {"point": [-0.53999996, 0.0, 1.28]},
  {"point": [0.34, -0.79999995, 1.9599999]},
  {"point": [0.34, 0.0, 1.9599999]},
  {"point": [1.06, -0.79999995, 1.68]},
  {"point": [1.06, 0.0, 1.68]},
  {"point": [1.62, -0.79999995, 1.14]},
  {"point": [1.62, 0.0, 1.14]},
  {"point": [1.9399999, -0.79999995, 0.42]},
  {"point": [1.9399999, 0.0, 0.42]},
  {"point": [1.9599999, -0.79999995, -0.34]},
  {"point": [1.9599999, 0.0, -0.34]},
  {"point": [1.68, -0.79999995, -1.06]},
  {"point": [1.68, 0.0, -1.06]},
  {"point": [1.14, -0.79999995, -1.62]},
  {"point": [1.14, 0.0, -1.62]},
  {"point": [0.42, -0.79999995, -1.9399999]},
  {"point": [0.42, 0.0, -1.9399999]},
  {"point": [-0.34, -0.79999995, -1.9599999]},
  {"point": [-0.34, 0.0, -1.9599999]},
  {"point": [-1.06, -0.79999995, -1.68]},
  {"point": [-1.06, 0.0, -1.68]},
  {"point": [-1.62, -0.79999995, -1.14]},
  {"point": [-1.62, 0.0, -1.14]},
  {"point": [-1.9399999, -0.79999995, -0.42]},
  {"point": [-1.9399999, 0.0, -0.42]},
  {"point": [-1.9599999, -0.79999995, 0.34]},
  {"point": [-1.9599999, 0.0, 0.34]},
  {"point": [-1.68, -0.79999995, 1.06]},
  {"point": [-1.68, 0.0, 1.06]},
  {"point": [-1.14, -0.79999995, 1.62]},
  {"point": [-1.14, 0.0, 1.62]},
  {"point": [-0.42, -0.79999995, 1.9399999]},
  {"point": [-0.42, 0.0, 1.9399999]}
]
